karaoke_lyrics_processor/__init__.py
karaoke_lyrics_processor/cli.py
karaoke_lyrics_processor/karaoke_lyrics_processor.py
karaoke_lyrics_processor-0.6.0.dist-info/LICENSE
karaoke_lyrics_processor-0.6.0.dist-info/METADATA
karaoke_lyrics_processor-0.6.0.dist-info/WHEEL
karaoke_lyrics_processor-0.6.0.dist-info/entry_points.txt
karaoke_lyrics_processor-0.6.0.dist-info/RECORD
