Metadata-Version: 2.3
Name: karaoke-lyrics-processor
Version: 0.6.0
Summary: Process song lyrics to prepare them for karaoke video production, e.g. by splitting long lines
License: MIT
Author: Andrew Beveridge
Author-email: andrew@beveridge.uk
Requires-Python: >=3.10,<4.0
Classifier: License :: OSI Approved :: MIT License
Classifier: Programming Language :: Python :: 3
Classifier: Programming Language :: Python :: 3.10
Classifier: Programming Language :: Python :: 3.11
Classifier: Programming Language :: Python :: 3.12
Classifier: Programming Language :: Python :: 3.13
Requires-Dist: docx2txt (>=0.8)
Requires-Dist: pyperclip (>=1.8)
Requires-Dist: python-docx (>=1)
Requires-Dist: striprtf (>=0.0.27)
Requires-Dist: textract-py3 (>=2.1.0)
Project-URL: Documentation, https://github.com/nomadkaraoke/karaoke-lyrics-processor/blob/main/README.md
Project-URL: Homepage, https://github.com/nomadkaraoke/karaoke-lyrics-processor
Project-URL: Repository, https://github.com/nomadkaraoke/karaoke-lyrics-processor
